reader/__init__.py
reader/__main__.py
reader/config.toml
reader/feed.py
reader/viewer.py
test_package_xyz_abc-0.1.2.dist-info/LICENSE
test_package_xyz_abc-0.1.2.dist-info/METADATA
test_package_xyz_abc-0.1.2.dist-info/WHEEL
test_package_xyz_abc-0.1.2.dist-info/RECORD
