Metadata-Version: 2.1
Name: test-package-xyz-abc
Version: 0.1.2
Summary: Test package
License: MIT
Author: Huw Jones
Author-email: huwdjones@hotmail.com
Requires-Python: >=3.11,<4.0
Classifier: License :: OSI Approved :: MIT License
Classifier: Programming Language :: Python :: 3
Classifier: Programming Language :: Python :: 3.11
Requires-Dist: feedparser (>=6.0.8,<7.0.0)
Requires-Dist: html2text (>=2020.1.16,<2021.0.0)
Requires-Dist: tomli (>=2.0.1,<3.0.0)
